{
  "type": "minecraft:entity",
  "pools": [
    {
      "rolls": 1,
      "entries": [
        {
          "type": "minecraft:item",
          "name": "supersentaicraft:red_racer_badge",
          "weight": 6
        },
        {
          "type": "minecraft:item",
          "name": "supersentaicraft:blue_racer_badge",
          "weight": 6
        },
        {
          "type": "minecraft:item",
          "name": "supersentaicraft:green_racer_badge",
          "weight": 6
        },
        {
          "type": "minecraft:item",
          "name": "supersentaicraft:yellow_racer_badge",
          "weight": 6
        },
        {
          "type": "minecraft:item",
          "name": "supersentaicraft:pink_racer_badge",
          "weight": 6
        },
        {
          "type": "minecraft:item",
          "name": "supersentaicraft:white_racer_badge"
        },
        {
          "type": "minecraft:item",
          "name": "supersentaicraft:signalman_badge"
        },
        {
          "type": "minecraft:item",
          "name": "supersentaicraft:vrv_master_badge"
        },
        {
          "type": "minecraft:item",
          "weight": 5,
          "name": "supersentaicraft:carranger_logo",
          "functions": [
            {
              "function": "minecraft:set_count",
              "count": 2
            }
          ]
        }
      ]
    },
    {
      "rolls": 1,
      "entries": [
        {
          "type": "minecraft:item",
          "name": "supersentaicraft:carranger_logo"
        }
      ]
    }
  ]
}